rsb_git/__init__.py
rsb_git/_git.py
rsb_git/_version.py
rs_artifactorypath-0.1.0.dist-info/LICENSE
rs_artifactorypath-0.1.0.dist-info/METADATA
rs_artifactorypath-0.1.0.dist-info/WHEEL
rs_artifactorypath-0.1.0.dist-info/top_level.txt
rs_artifactorypath-0.1.0.dist-info/RECORD
