Metadata-Version: 2.1
Name: rs_artifactorypath
Version: 0.1.0
Summary: High level interface for git functionality
License: License: Proprietary Rohde & Schwarz
Requires-Python: >=3.8
License-File: LICENSE
